README.md
setup.py
crunchapilyb/__init__.py
crunchapilyb/crunchapi.py
crunchapilyb/key.py
crunchapilyb/records.py
crunchapilyb/trigger.py
crunchapilyb.egg-info/PKG-INFO
crunchapilyb.egg-info/SOURCES.txt
crunchapilyb.egg-info/dependency_links.txt
crunchapilyb.egg-info/requires.txt
crunchapilyb.egg-info/top_level.txt