Metadata-Version: 1.0
Name: crunchapilyb
Version: 1.0.0
Summary: A Crunch API by Christopher
Home-page: https://github.com/ChristopherLiu618/CrunchAPI
Author: Yibang (Christopher) Liu
Author-email: yibang.christopher.liu@gmail.com
License: Apache
Keywords: pandas,Crunch,API
Platform: any
